{"friends": [{"username": "kdobbin", "city": "Toronto", "userpic_url": "https://drscdn.500px.org/user_avatar/20935939/q%3D85_w%3D300_h%3D300/v2?webp=true&v=1&sig=28298eff4d1f176bf0717e962ad4bb9edac8e4486c5b7834b54f799dc04546b2", "store_on": true, "userpic_https_url": "https://drscdn.500px.org/user_avatar/20935939/q%3D85_w%3D300_h%3D300/v2?webp=true&v=1&sig=28298eff4d1f176bf0717e962ad4bb9edac8e4486c5b7834b54f799dc04546b2", "firstname": "Kristen", "lastname": "Dobbin", "upgrade_status": 0, "avatars": {"default": {"https": "https://drscdn.500px.org/user_avatar/20935939/q%3D85_w%3D300_h%3D300/v2?webp=true&v=1&sig=28298eff4d1f176bf0717e962ad4bb9edac8e4486c5b7834b54f799dc04546b2"}, "large": {"https": "https://drscdn.500px.org/user_avatar/20935939/q%3D85_w%3D100_h%3D100/v2?webp=true&v=1&sig=ca143e8c996871b94ea4bc229d13bf66ed0bc01255605bcb2bffa0dbf99559cb"}, "small": {"https": "https://drscdn.500px.org/user_avatar/20935939/q%3D85_w%3D50_h%3D50/v2?webp=true&v=1&sig=cec8af5fc34a3b58167fc573e2b17304c0e7a2108c5e14af47f207aecced2eac"}, "tiny": {"https": "https://drscdn.500px.org/user_avatar/20935939/q%3D85_w%3D30_h%3D30/v2?webp=true&v=1&sig=89edd084b011393153ec308e17946b585d607363cc72128500ba9f2d27088eef"}}, "cover_url": "https://drscdn.500px.org/user_cover/20935939/q%3D65_m%3D2048/v2?webp=true&v=1&sig=d13aa5344e7e13cb2b6441f0315080dd382b1cdb3a6486985b937612ffc2c921", "usertype": 13, "followers_count": 359, "country": "Canada", "fullname": "Kristen Dobbin", "id": 20935939, "affection": 811}, {"username": "RodrigoDaguerre", "city": "Toronto", "userpic_url": "https://graph.facebook.com/v2.7/10157397708805150/picture?height=100&width=100", "store_on": true, "userpic_https_url": "https://graph.facebook.com/v2.7/10157397708805150/picture?height=100&width=100", "firstname": "Rodrigo", "lastname": "Daguerre", "upgrade_status": 4, "avatars": {"default": {"https": "https://graph.facebook.com/v2.7/10157397708805150/picture?height=100&width=100"}, "large": {"https": "https://graph.facebook.com/v2.7/10157397708805150/picture?height=100&width=100"}, "small": {"https": "https://graph.facebook.com/v2.7/10157397708805150/picture?height=100&width=100"}, "tiny": {"https": "https://graph.facebook.com/v2.7/10157397708805150/picture?height=100&width=100"}}, "cover_url": "https://drscdn.500px.org/user_cover/19424221/q%3D65_m%3D2048/v2?webp=true&v=3&sig=c2e6c17c07eb2021e222563218e25070db6f334b43cf81081e440c55df23b8bc", "usertype": 13, "followers_count": 22146, "country": "Canada", "fullname": "Rodrigo Daguerre", "id": 19424221, "affection": 15295}, {"username": "ArynaPushkevich", "city": "Minsk", "userpic_url": "https://drscdn.500px.org/user_avatar/18037179/q%3D85_w%3D300_h%3D300/v2?webp=true&v=8&sig=6ba682738602eea9986d71aa0aa8623064ad8893fff36cfeffec5d2dab33550d", "store_on": false, "userpic_https_url": "https://drscdn.500px.org/user_avatar/18037179/q%3D85_w%3D300_h%3D300/v2?webp=true&v=8&sig=6ba682738602eea9986d71aa0aa8623064ad8893fff36cfeffec5d2dab33550d", "firstname": "Aryna", "lastname": "Pushkevich", "upgrade_status": 0, "avatars": {"default": {"https": "https://drscdn.500px.org/user_avatar/18037179/q%3D85_w%3D300_h%3D300/v2?webp=true&v=8&sig=6ba682738602eea9986d71aa0aa8623064ad8893fff36cfeffec5d2dab33550d"}, "large": {"https": "https://drscdn.500px.org/user_avatar/18037179/q%3D85_w%3D100_h%3D100/v2?webp=true&v=8&sig=b44af6fec0dd41155e54a435b8561475989f2a24856c5ef354753b1c065e0b6b"}, "small": {"https": "https://drscdn.500px.org/user_avatar/18037179/q%3D85_w%3D50_h%3D50/v2?webp=true&v=8&sig=168d7090ddc23f587442bae754d6e85fef9a54105c0df9f2d4ba6488d9e9c87c"}, "tiny": {"https": "https://drscdn.500px.org/user_avatar/18037179/q%3D85_w%3D30_h%3D30/v2?webp=true&v=8&sig=7ccd4865f1bd3028f93ae30dcf91bf720e6715461341d870f486177151fbd027"}}, "cover_url": "https://drscdn.500px.org/user_cover/18037179/q%3D65_m%3D2048/v2?webp=true&v=1&sig=7e3362e4c849fc5a004b2b345df1833879e35faa3a2fba1bb22d1501e1536b43", "usertype": 0, "followers_count": 150, "country": "Belarus", "fullname": "Aryna Pushkevich", "id": 18037179, "affection": 9971}, {"username": "steph_juliet", "city": "Toronto", "userpic_url": "https://drscdn.500px.org/user_avatar/15946201/q%3D85_w%3D300_h%3D300/v2?webp=true&v=1&sig=1d09b4f252789ed35bfe4117762ff7f05a701c3251e2da4155edaef47d6e3ded", "store_on": true, "userpic_https_url": "https://drscdn.500px.org/user_avatar/15946201/q%3D85_w%3D300_h%3D300/v2?webp=true&v=1&sig=1d09b4f252789ed35bfe4117762ff7f05a701c3251e2da4155edaef47d6e3ded", "firstname": "Stephanie Juliet", "admin": 1, "lastname": "Algieri", "upgrade_status": 4, "avatars": {"default": {"https": "https://drscdn.500px.org/user_avatar/15946201/q%3D85_w%3D300_h%3D300/v2?webp=true&v=1&sig=1d09b4f252789ed35bfe4117762ff7f05a701c3251e2da4155edaef47d6e3ded"}, "large": {"https": "https://drscdn.500px.org/user_avatar/15946201/q%3D85_w%3D100_h%3D100/v2?webp=true&v=1&sig=04ef57f3d37ad6b49efeea0f6c1214c209026d3b8543fc6e3648b44b4a5ba9e9"}, "small": {"https": "https://drscdn.500px.org/user_avatar/15946201/q%3D85_w%3D50_h%3D50/v2?webp=true&v=1&sig=a672a627c0f8fb3132ea45461e6953eae86c44e762caaf038dc193e644bf39d2"}, "tiny": {"https": "https://drscdn.500px.org/user_avatar/15946201/q%3D85_w%3D30_h%3D30/v2?webp=true&v=1&sig=f030080dfe36e3ecb907b638334ce48304cabfa8403b864a18fb5d596928493b"}}, "cover_url": "https://drscdn.500px.org/user_cover/15946201/q%3D65_m%3D2048/v2?webp=true&v=2&sig=4a7682a8e4501e0a4490f212cbd9970558f8cc2f014026c2d8b883ec0034dd17", "usertype": 9, "followers_count": 240, "country": "Canada", "fullname": "Stephanie Juliet Algieri", "id": 15946201, "affection": 1902}, {"username": "aroyamotos", "city": "Toronto", "userpic_url": "https://drscdn.500px.org/user_avatar/13759947/q%3D85_w%3D300_h%3D300/v2?webp=true&v=11&sig=dc860dc625a7da1d1576b2197f86601476e36debca1322835bcb571f9e38cb2e", "store_on": true, "userpic_https_url": "https://drscdn.500px.org/user_avatar/13759947/q%3D85_w%3D300_h%3D300/v2?webp=true&v=11&sig=dc860dc625a7da1d1576b2197f86601476e36debca1322835bcb571f9e38cb2e", "firstname": "Anthony", "lastname": "Sotomayor", "upgrade_status": 3, "avatars": {"default": {"https": "https://drscdn.500px.org/user_avatar/13759947/q%3D85_w%3D300_h%3D300/v2?webp=true&v=11&sig=dc860dc625a7da1d1576b2197f86601476e36debca1322835bcb571f9e38cb2e"}, "large": {"https": "https://drscdn.500px.org/user_avatar/13759947/q%3D85_w%3D100_h%3D100/v2?webp=true&v=11&sig=25c84361baaac4b8378362bee8dc4b97028c252b610e973e6612cda1057eae7a"}, "small": {"https": "https://drscdn.500px.org/user_avatar/13759947/q%3D85_w%3D50_h%3D50/v2?webp=true&v=11&sig=c36b272f8e91fabd51abecb3426ea2aa264e07155ff409e9fe0810cd2222a410"}, "tiny": {"https": "https://drscdn.500px.org/user_avatar/13759947/q%3D85_w%3D30_h%3D30/v2?webp=true&v=11&sig=30729ced1349e5130a3ce3aa769d2e9f4a391f4be63d01255c1de01692745339"}}, "cover_url": "https://drscdn.500px.org/user_cover/13759947/q%3D65_m%3D2048/v2?webp=true&v=10&sig=f64255d4d22d7e84f15f754f09422eaf1a07f435d1d2210cadc5da06d509065c", "usertype": 10, "followers_count": 201179, "country": "Canada", "fullname": "Anthony Sotomayor", "id": 13759947, "affection": 182643}, {"username": "LaureenBurton1", "city": "Quebec City", "userpic_url": "https://drscdn.500px.org/user_avatar/13264837/q%3D85_w%3D300_h%3D300/v2?webp=true&v=5&sig=0f663694d676b5f4cb420f7af5566832955a34425b81bd1f521d38ed032370c2", "store_on": true, "userpic_https_url": "https://drscdn.500px.org/user_avatar/13264837/q%3D85_w%3D300_h%3D300/v2?webp=true&v=5&sig=0f663694d676b5f4cb420f7af5566832955a34425b81bd1f521d38ed032370c2", "firstname": "Laureen", "lastname": "Burton", "upgrade_status": 2, "avatars": {"default": {"https": "https://drscdn.500px.org/user_avatar/13264837/q%3D85_w%3D300_h%3D300/v2?webp=true&v=5&sig=0f663694d676b5f4cb420f7af5566832955a34425b81bd1f521d38ed032370c2"}, "large": {"https": "https://drscdn.500px.org/user_avatar/13264837/q%3D85_w%3D100_h%3D100/v2?webp=true&v=5&sig=d14b6017ac3de97def461247e5cc1d960224fe16aa82eef0cceffb3739d3de97"}, "small": {"https": "https://drscdn.500px.org/user_avatar/13264837/q%3D85_w%3D50_h%3D50/v2?webp=true&v=5&sig=26b493a69fc1d0cb1a2967b86b76ef3746801d7c1b3312e881f15e25ccd56700"}, "tiny": {"https": "https://drscdn.500px.org/user_avatar/13264837/q%3D85_w%3D30_h%3D30/v2?webp=true&v=5&sig=94e3a08e19fbdc540ff0cda8685456005ba3e28d09207a4a9e0a2bad6d5718cd"}}, "cover_url": "https://drscdn.500px.org/user_cover/13264837/q%3D65_m%3D2048/v2?webp=true&v=17&sig=720e23c2c8b1c8caa12f56a1e29da8f6fea4e9e09f16000e83121947827cfb41", "usertype": 0, "followers_count": 129968, "country": "Canada", "fullname": "Laureen Burton", "id": 13264837, "affection": 556252}, {"username": "60th_kid", "city": "Minneapolis", "userpic_url": "https://drscdn.500px.org/user_avatar/10293639/q%3D85_w%3D300_h%3D300/v2?webp=true&v=1&sig=7b91b5fbcc29b4be1a6148b8769e0c478174e09109f47152b6463f6279b49885", "store_on": true, "userpic_https_url": "https://drscdn.500px.org/user_avatar/10293639/q%3D85_w%3D300_h%3D300/v2?webp=true&v=1&sig=7b91b5fbcc29b4be1a6148b8769e0c478174e09109f47152b6463f6279b49885", "firstname": "kyle", "lastname": "Gendreau", "upgrade_status": 0, "avatars": {"default": {"https": "https://drscdn.500px.org/user_avatar/10293639/q%3D85_w%3D300_h%3D300/v2?webp=true&v=1&sig=7b91b5fbcc29b4be1a6148b8769e0c478174e09109f47152b6463f6279b49885"}, "large": {"https": "https://drscdn.500px.org/user_avatar/10293639/q%3D85_w%3D100_h%3D100/v2?webp=true&v=1&sig=93547946bde6cd530b209e2e08a50b67c65930b7ea01f79951ceafb4641a0b34"}, "small": {"https": "https://drscdn.500px.org/user_avatar/10293639/q%3D85_w%3D50_h%3D50/v2?webp=true&v=1&sig=45f80c6de08aa10786f645ddc5a09a010f49fe9c4e0e740a221e5ea3523fa0b9"}, "tiny": {"https": "https://drscdn.500px.org/user_avatar/10293639/q%3D85_w%3D30_h%3D30/v2?webp=true&v=1&sig=f5a0967441b9513c5f76395505d8b82afd3b5c108141fae003695b408f80e0d0"}}, "cover_url": "https://drscdn.500px.org/user_cover/10293639/q%3D65_m%3D2048/v2?webp=true&v=3&sig=dc9c3ea8369dee9575fa41c5f06c18f5152a82d89eec5f55e07aa44232b29108", "usertype": 0, "followers_count": 100, "country": "US", "fullname": "kyle Gendreau", "id": 10293639, "affection": 450}, {"username": "eladavidnissim", "city": "jerusalem", "userpic_url": "https://drscdn.500px.org/user_avatar/7218013/q%3D85_w%3D300_h%3D300/v2?webp=true&v=4&sig=3a3f14c6d1153b2459abba75b20183f243a0a82f9ebedda7a971ca09b9380112", "store_on": true, "userpic_https_url": "https://drscdn.500px.org/user_avatar/7218013/q%3D85_w%3D300_h%3D300/v2?webp=true&v=4&sig=3a3f14c6d1153b2459abba75b20183f243a0a82f9ebedda7a971ca09b9380112", "firstname": "Elad ", "lastname": "Nissim", "upgrade_status": 0, "avatars": {"default": {"https": "https://drscdn.500px.org/user_avatar/7218013/q%3D85_w%3D300_h%3D300/v2?webp=true&v=4&sig=3a3f14c6d1153b2459abba75b20183f243a0a82f9ebedda7a971ca09b9380112"}, "large": {"https": "https://drscdn.500px.org/user_avatar/7218013/q%3D85_w%3D100_h%3D100/v2?webp=true&v=4&sig=ac02d0e338ce447047e46d8e5e6027ea8d18e45f344f6a4e0b27ad29bc4ebbda"}, "small": {"https": "https://drscdn.500px.org/user_avatar/7218013/q%3D85_w%3D50_h%3D50/v2?webp=true&v=4&sig=ba840178ad73a0e1a08667c6412d0630f62a4e44d4d7748c5486428a34152b9d"}, "tiny": {"https": "https://drscdn.500px.org/user_avatar/7218013/q%3D85_w%3D30_h%3D30/v2?webp=true&v=4&sig=9b22160a13b67cf2f2477594e27d62111ea02fd6c719210712a2fbf78544126a"}}, "cover_url": "https://drscdn.500px.org/user_cover/7218013/q%3D65_m%3D2048/v2?webp=true&v=17&sig=f995f68d5980eddf845695f961ebea933d2e3d21326b1d7a061cf2493d3ff0d8", "usertype": 0, "followers_count": 140887, "country": "israel", "fullname": "Elad  Nissim", "id": 7218013, "affection": 93234}, {"username": "thebrianwilson", "city": "Toronto", "userpic_url": "https://drscdn.500px.org/user_avatar/6416110/q%3D85_w%3D300_h%3D300/v2?webp=true&v=7&sig=aa12903e61fa7c78115fe7483cc536f6a15823dca82280073db6ec11cbbed3fe", "store_on": false, "userpic_https_url": "https://drscdn.500px.org/user_avatar/6416110/q%3D85_w%3D300_h%3D300/v2?webp=true&v=7&sig=aa12903e61fa7c78115fe7483cc536f6a15823dca82280073db6ec11cbbed3fe", "firstname": "Brian", "lastname": "Wilson", "upgrade_status": 4, "avatars": {"default": {"https": "https://drscdn.500px.org/user_avatar/6416110/q%3D85_w%3D300_h%3D300/v2?webp=true&v=7&sig=aa12903e61fa7c78115fe7483cc536f6a15823dca82280073db6ec11cbbed3fe"}, "large": {"https": "https://drscdn.500px.org/user_avatar/6416110/q%3D85_w%3D100_h%3D100/v2?webp=true&v=7&sig=a90fe8c875476ee0aaee5937b7ab67a5588d9e02c4dc9c5be7c5dbf976a1adaf"}, "small": {"https": "https://drscdn.500px.org/user_avatar/6416110/q%3D85_w%3D50_h%3D50/v2?webp=true&v=7&sig=e4524efe6f33395735c54bf34e60569101191a50205849a275e39d19b0a0334e"}, "tiny": {"https": "https://drscdn.500px.org/user_avatar/6416110/q%3D85_w%3D30_h%3D30/v2?webp=true&v=7&sig=5f501cc91df4dc6dc2de58feeda25c5b1761f600e5a753f6ceb7a4ff23e617fd"}}, "cover_url": "https://drscdn.500px.org/user_cover/6416110/q%3D65_m%3D2048/v2?webp=true&v=3&sig=0379c0541ef67697a798f4b1e0561977d587c32658019f1d3f4ecf6748b434bd", "usertype": 13, "followers_count": 3391, "country": "Canada", "fullname": "Brian Wilson", "id": 6416110, "affection": 11381}, {"username": "Gurkan-Gundogdu", "city": "Istanbul", "userpic_url": "https://drscdn.500px.org/user_avatar/5242176/q%3D85_w%3D300_h%3D300/v2?webp=true&v=11&sig=f746c4a96b0f5e0a138f7bfeae1a4aa27c7dd4cc11c0e7b90771a35e1746956a", "store_on": true, "userpic_https_url": "https://drscdn.500px.org/user_avatar/5242176/q%3D85_w%3D300_h%3D300/v2?webp=true&v=11&sig=f746c4a96b0f5e0a138f7bfeae1a4aa27c7dd4cc11c0e7b90771a35e1746956a", "firstname": "G\u00fcrkan", "lastname": "G\u00fcndogdu", "upgrade_status": 0, "avatars": {"default": {"https": "https://drscdn.500px.org/user_avatar/5242176/q%3D85_w%3D300_h%3D300/v2?webp=true&v=11&sig=f746c4a96b0f5e0a138f7bfeae1a4aa27c7dd4cc11c0e7b90771a35e1746956a"}, "large": {"https": "https://drscdn.500px.org/user_avatar/5242176/q%3D85_w%3D100_h%3D100/v2?webp=true&v=11&sig=7ca24584fc197f4ec4045cd2dd624679f7bec1f60245629fcf8c5024d2b6a0fc"}, "small": {"https": "https://drscdn.500px.org/user_avatar/5242176/q%3D85_w%3D50_h%3D50/v2?webp=true&v=11&sig=c575560bb4807f0b8e982949c4d5b613f33f4f00b388e03d10155761afc79c69"}, "tiny": {"https": "https://drscdn.500px.org/user_avatar/5242176/q%3D85_w%3D30_h%3D30/v2?webp=true&v=11&sig=13129e5ecb0e586638e5a55e9077c47e3ac49fc71db811f566e60d1f670aa176"}}, "cover_url": "https://drscdn.500px.org/user_cover/5242176/q%3D65_m%3D2048/v2?webp=true&v=9&sig=d1553ef95c9019d09412b183d4922e3ae58d9d7bd50490451dfb33bb58197cc1", "usertype": 0, "followers_count": 13381, "country": "T\u00fcrkiye", "fullname": "G\u00fcrkan G\u00fcndogdu", "id": 5242176, "affection": 899283}, {"username": "7wanderer7", "city": "Northern Europe", "userpic_url": "https://drscdn.500px.org/user_avatar/4532328/q%3D85_w%3D300_h%3D300/v2?webp=true&v=17&sig=1c2e745b7ca7a111ff64527d560ab10f580a9fdc734c942a843ea97743a7330c", "store_on": true, "userpic_https_url": "https://drscdn.500px.org/user_avatar/4532328/q%3D85_w%3D300_h%3D300/v2?webp=true&v=17&sig=1c2e745b7ca7a111ff64527d560ab10f580a9fdc734c942a843ea97743a7330c", "firstname": "\u017dygimantas", "lastname": "Jagelavi\u010dius", "upgrade_status": 0, "avatars": {"default": {"https": "https://drscdn.500px.org/user_avatar/4532328/q%3D85_w%3D300_h%3D300/v2?webp=true&v=17&sig=1c2e745b7ca7a111ff64527d560ab10f580a9fdc734c942a843ea97743a7330c"}, "large": {"https": "https://drscdn.500px.org/user_avatar/4532328/q%3D85_w%3D100_h%3D100/v2?webp=true&v=17&sig=8aaec6fa5e058ef50c84f938915db0e04cdb41daacf03496defabeaa34522dd0"}, "small": {"https": "https://drscdn.500px.org/user_avatar/4532328/q%3D85_w%3D50_h%3D50/v2?webp=true&v=17&sig=db8000ae0eec0adfe851e4e26418525438d2d1739a787171f3f0b07fa15a1b3d"}, "tiny": {"https": "https://drscdn.500px.org/user_avatar/4532328/q%3D85_w%3D30_h%3D30/v2?webp=true&v=17&sig=9963005efab7abccd799e826941074d2cd1635a08857d27fee2a64efae9314f1"}}, "cover_url": "https://drscdn.500px.org/user_cover/4532328/q%3D65_m%3D2048/v2?webp=true&v=11&sig=d3cfd10a789d7ac3b449b8d7c05243a3aab44a70fdd5ab4df885e56b80e291cd", "usertype": 0, "followers_count": 142, "country": "Lithuania, Kaunas", "fullname": "\u017dygimantas Jagelavi\u010dius", "id": 4532328, "affection": 1339}, {"username": "belelula", "city": "Madrid", "userpic_url": "https://drscdn.500px.org/user_avatar/2788127/q%3D85_w%3D300_h%3D300/v2?webp=true&v=6&sig=fe610c70fa12d631c1ab284b3bea972fe9041e546f6ccb1de51a42a804b6893e", "store_on": true, "userpic_https_url": "https://drscdn.500px.org/user_avatar/2788127/q%3D85_w%3D300_h%3D300/v2?webp=true&v=6&sig=fe610c70fa12d631c1ab284b3bea972fe9041e546f6ccb1de51a42a804b6893e", "firstname": "Olga", "lastname": "May", "upgrade_status": 0, "avatars": {"default": {"https": "https://drscdn.500px.org/user_avatar/2788127/q%3D85_w%3D300_h%3D300/v2?webp=true&v=6&sig=fe610c70fa12d631c1ab284b3bea972fe9041e546f6ccb1de51a42a804b6893e"}, "large": {"https": "https://drscdn.500px.org/user_avatar/2788127/q%3D85_w%3D100_h%3D100/v2?webp=true&v=6&sig=64c780945648528668f61c5912747c55d39b503becbd559aad9b39db4c530beb"}, "small": {"https": "https://drscdn.500px.org/user_avatar/2788127/q%3D85_w%3D50_h%3D50/v2?webp=true&v=6&sig=dd998672da6cb999c9cd6acb5ddc839cd78810d15f60e92195a30c0a5fa5d57a"}, "tiny": {"https": "https://drscdn.500px.org/user_avatar/2788127/q%3D85_w%3D30_h%3D30/v2?webp=true&v=6&sig=3c68c3fb21d971a09aafc9a37ec86f25a5205bc5279ec6450a726d797137ce34"}}, "cover_url": "https://drscdn.500px.org/user_cover/2788127/q%3D65_m%3D2048/v2?webp=true&v=5&sig=89863f1763bc5ed635ea7c47b2b41e7d91419f00a4becb4f6d910cfa355105e0", "usertype": 0, "followers_count": 228, "country": "Espa\u00f1a", "fullname": "Olga May", "id": 2788127, "affection": 8000}, {"username": "MasashiMitsui", "city": "Tokyo", "userpic_url": "https://drscdn.500px.org/user_avatar/2769227/q%3D85_w%3D300_h%3D300/v2?webp=true&v=2&sig=d60f12b39d94b75a8741629d468dd174e766b7c6624d321536971976555967eb", "store_on": true, "userpic_https_url": "https://drscdn.500px.org/user_avatar/2769227/q%3D85_w%3D300_h%3D300/v2?webp=true&v=2&sig=d60f12b39d94b75a8741629d468dd174e766b7c6624d321536971976555967eb", "firstname": "Masashi", "lastname": "Mitsui", "upgrade_status": 2, "avatars": {"default": {"https": "https://drscdn.500px.org/user_avatar/2769227/q%3D85_w%3D300_h%3D300/v2?webp=true&v=2&sig=d60f12b39d94b75a8741629d468dd174e766b7c6624d321536971976555967eb"}, "large": {"https": "https://drscdn.500px.org/user_avatar/2769227/q%3D85_w%3D100_h%3D100/v2?webp=true&v=2&sig=0311a39acaedcfbd9d731097d7987322f5e747666ec4270b6e00fbe562ba6a74"}, "small": {"https": "https://drscdn.500px.org/user_avatar/2769227/q%3D85_w%3D50_h%3D50/v2?webp=true&v=2&sig=2e93e1f41dfce9e0fdb53d8371f2b63edb95ee738dd42d44cbd13482e765f157"}, "tiny": {"https": "https://drscdn.500px.org/user_avatar/2769227/q%3D85_w%3D30_h%3D30/v2?webp=true&v=2&sig=e172bafc4119bcd9ab421cd14294b23e64ef6fb41e9fba613a02822511c3f37a"}}, "cover_url": null, "usertype": 0, "followers_count": 6418, "country": "Japan", "fullname": "Masashi Mitsui", "id": 2769227, "affection": 44869}, {"username": "diverstef", "city": "Chaloklum, Koh Pha Ngan", "userpic_url": "https://drscdn.500px.org/user_avatar/1897843/q%3D85_w%3D300_h%3D300/v2?webp=true&v=3&sig=1d4497467ccc8701a451f7b3f6f58ca721dd140181dccd3c052cbfba8ee002dc", "store_on": true, "userpic_https_url": "https://drscdn.500px.org/user_avatar/1897843/q%3D85_w%3D300_h%3D300/v2?webp=true&v=3&sig=1d4497467ccc8701a451f7b3f6f58ca721dd140181dccd3c052cbfba8ee002dc", "firstname": "Stefan", "lastname": "Follows", "upgrade_status": 0, "avatars": {"default": {"https": "https://drscdn.500px.org/user_avatar/1897843/q%3D85_w%3D300_h%3D300/v2?webp=true&v=3&sig=1d4497467ccc8701a451f7b3f6f58ca721dd140181dccd3c052cbfba8ee002dc"}, "large": {"https": "https://drscdn.500px.org/user_avatar/1897843/q%3D85_w%3D100_h%3D100/v2?webp=true&v=3&sig=d331bf0f49d98e3745616fd35166c0bd9e15f60e5ba800f088bffde017474b42"}, "small": {"https": "https://drscdn.500px.org/user_avatar/1897843/q%3D85_w%3D50_h%3D50/v2?webp=true&v=3&sig=afd585b83a1e9ddce8f3ba9862d08b5bb16590cee9cebf1799491d3756b4401d"}, "tiny": {"https": "https://drscdn.500px.org/user_avatar/1897843/q%3D85_w%3D30_h%3D30/v2?webp=true&v=3&sig=30d35f63d743f17a9161b143cde06d662bbdef6c6e6cebd8bb258cf83f355046"}}, "cover_url": "https://drscdn.500px.org/user_cover/1897843/q%3D65_m%3D2048/v2?webp=true&v=3&sig=8e215dca84ba4c102d88e86df12fc9fefec62110d6048fe4e1156f1ca6c8f9a4", "usertype": 0, "followers_count": 75851, "country": "Thailand", "fullname": "Stefan Follows", "id": 1897843, "affection": 100646}, {"username": "DanielaTade", "city": "Buenos Aires", "userpic_url": "https://drscdn.500px.org/user_avatar/883252/q%3D85_w%3D300_h%3D300/v2?webp=true&v=3&sig=fd4808bdfe5e62fdcb8838d2e8c079ad0cc21e1d9b5b53793ab831d0c6e6710d", "store_on": true, "userpic_https_url": "https://drscdn.500px.org/user_avatar/883252/q%3D85_w%3D300_h%3D300/v2?webp=true&v=3&sig=fd4808bdfe5e62fdcb8838d2e8c079ad0cc21e1d9b5b53793ab831d0c6e6710d", "firstname": "Daniela", "lastname": "Tad\u00e9", "upgrade_status": 0, "avatars": {"default": {"https": "https://drscdn.500px.org/user_avatar/883252/q%3D85_w%3D300_h%3D300/v2?webp=true&v=3&sig=fd4808bdfe5e62fdcb8838d2e8c079ad0cc21e1d9b5b53793ab831d0c6e6710d"}, "large": {"https": "https://drscdn.500px.org/user_avatar/883252/q%3D85_w%3D100_h%3D100/v2?webp=true&v=3&sig=11262a9d4a10d7cc9f7f30803d6d5cd69cf4f37f7c409aae6e20f97425156aac"}, "small": {"https": "https://drscdn.500px.org/user_avatar/883252/q%3D85_w%3D50_h%3D50/v2?webp=true&v=3&sig=39d841c770a65544579fa3bf4949b9ce5825b527f0b897378200c7ac7769378f"}, "tiny": {"https": "https://drscdn.500px.org/user_avatar/883252/q%3D85_w%3D30_h%3D30/v2?webp=true&v=3&sig=d5c63db246cf1563a62dfe3988b25db71acaa5466cc95a5a536194a87e561c37"}}, "cover_url": "https://drscdn.500px.org/user_cover/883252/q%3D65_m%3D2048/v2?webp=true&v=6&sig=6a7cae9c9d737e21d8557397e023f496f95681c3c712d2405da8b8cba4f452d4", "usertype": 0, "followers_count": 142, "country": "Argentina", "fullname": "Daniela Tad\u00e9", "id": 883252, "affection": 1613}, {"username": "timgaweco", "city": "Toronto", "userpic_url": "https://drscdn.500px.org/user_avatar/706350/q%3D85_w%3D300_h%3D300/v2?webp=true&v=8&sig=c589bee547fbca08d4b0ee33d395c0acd04d2af486920768fb1b671856840db3", "store_on": true, "userpic_https_url": "https://drscdn.500px.org/user_avatar/706350/q%3D85_w%3D300_h%3D300/v2?webp=true&v=8&sig=c589bee547fbca08d4b0ee33d395c0acd04d2af486920768fb1b671856840db3", "firstname": "Tim", "lastname": "Gaweco", "upgrade_status": 3, "avatars": {"default": {"https": "https://drscdn.500px.org/user_avatar/706350/q%3D85_w%3D300_h%3D300/v2?webp=true&v=8&sig=c589bee547fbca08d4b0ee33d395c0acd04d2af486920768fb1b671856840db3"}, "large": {"https": "https://drscdn.500px.org/user_avatar/706350/q%3D85_w%3D100_h%3D100/v2?webp=true&v=8&sig=7315154a37960da315b297ba05f9269b5c6e8778d271bfd72d0e41754409d8ef"}, "small": {"https": "https://drscdn.500px.org/user_avatar/706350/q%3D85_w%3D50_h%3D50/v2?webp=true&v=8&sig=6732a0a5b1bc5a906cceab859a3769e8e5f6c8657452d8948297f4b89a07c7e8"}, "tiny": {"https": "https://drscdn.500px.org/user_avatar/706350/q%3D85_w%3D30_h%3D30/v2?webp=true&v=8&sig=b5c0cc508e58c91cf63e3dfd1ff16b0f46bcbf4c431fe12b79f222e618989d90"}}, "cover_url": "https://drscdn.500px.org/user_cover/706350/q%3D65_m%3D2048/v2?webp=true&v=29&sig=f3b61d2688efe43a99ad52eb554ed7bd11e43dcc79cab23d91a98efc60654be2", "usertype": 0, "followers_count": 18133, "country": "Canada", "fullname": "Tim Gaweco", "id": 706350, "affection": 185977}, {"username": "SamAlive", "city": "Brooklyn", "userpic_url": "https://drscdn.500px.org/user_avatar/627480/q%3D85_w%3D300_h%3D300/v2?webp=true&v=17&sig=b0abadcbfec7d0bd6da09bc915ee10838ac775b535ce8d590948735b349d2019", "store_on": true, "userpic_https_url": "https://drscdn.500px.org/user_avatar/627480/q%3D85_w%3D300_h%3D300/v2?webp=true&v=17&sig=b0abadcbfec7d0bd6da09bc915ee10838ac775b535ce8d590948735b349d2019", "firstname": "Sam", "lastname": "Alive", "upgrade_status": 0, "avatars": {"default": {"https": "https://drscdn.500px.org/user_avatar/627480/q%3D85_w%3D300_h%3D300/v2?webp=true&v=17&sig=b0abadcbfec7d0bd6da09bc915ee10838ac775b535ce8d590948735b349d2019"}, "large": {"https": "https://drscdn.500px.org/user_avatar/627480/q%3D85_w%3D100_h%3D100/v2?webp=true&v=17&sig=b8a725e06ec1c0e67653d019c0d98998fd98d6ca0448bd14ca0e55227dd82424"}, "small": {"https": "https://drscdn.500px.org/user_avatar/627480/q%3D85_w%3D50_h%3D50/v2?webp=true&v=17&sig=4f2f04c6c5fe3eae5019bd24fb99026ddb5830f0a8cfaf044c3ab06571378d5c"}, "tiny": {"https": "https://drscdn.500px.org/user_avatar/627480/q%3D85_w%3D30_h%3D30/v2?webp=true&v=17&sig=68b7b48943d6890af2cddb9f8635516738d8d9bbc2867f12a8c31e0f2e8ab4c8"}}, "cover_url": "https://drscdn.500px.org/user_cover/627480/q%3D65_m%3D2048/v2?webp=true&v=9&sig=4ad6b76a52be3f6f778bee09fa9cc4c9318dc16ed137e00bcddce0dd23efafd0", "usertype": 0, "followers_count": 223190, "country": "United States", "fullname": "Sam Alive", "id": 627480, "affection": 334661}, {"username": "NitishMeena", "city": "Seattle", "userpic_url": "https://drscdn.500px.org/user_avatar/501351/q%3D85_w%3D300_h%3D300/v2?webp=true&v=4&sig=204217b0c2a16a723a08464c6cb231622299028550f317a37600ed2c2ea9bccd", "store_on": true, "userpic_https_url": "https://drscdn.500px.org/user_avatar/501351/q%3D85_w%3D300_h%3D300/v2?webp=true&v=4&sig=204217b0c2a16a723a08464c6cb231622299028550f317a37600ed2c2ea9bccd", "firstname": "Nitish Kumar", "lastname": "Meena", "upgrade_status": 2, "avatars": {"default": {"https": "https://drscdn.500px.org/user_avatar/501351/q%3D85_w%3D300_h%3D300/v2?webp=true&v=4&sig=204217b0c2a16a723a08464c6cb231622299028550f317a37600ed2c2ea9bccd"}, "large": {"https": "https://drscdn.500px.org/user_avatar/501351/q%3D85_w%3D100_h%3D100/v2?webp=true&v=4&sig=3017a62f029e229147bed2ea1cb6288615365285474366ecc764f03d1e3fdf07"}, "small": {"https": "https://drscdn.500px.org/user_avatar/501351/q%3D85_w%3D50_h%3D50/v2?webp=true&v=4&sig=4ac844549f0e9ab4adfee8157159d28ee996aafdd2fb73844ff7bc40cb6b52a7"}, "tiny": {"https": "https://drscdn.500px.org/user_avatar/501351/q%3D85_w%3D30_h%3D30/v2?webp=true&v=4&sig=6f98ebdfb07b335061ed5c844e3993eb5ea5c36c295f4e0599b06e084bf73dc8"}}, "cover_url": "https://drscdn.500px.org/user_cover/501351/q%3D65_m%3D2048/v2?webp=true&v=19&sig=b43a43de9db524e18a1b5ef54aae8b0329bb991ee101b33b39c040c7562b0f1f", "usertype": 0, "followers_count": 822, "country": "USA", "fullname": "Nitish Kumar Meena", "id": 501351, "affection": 23472}, {"username": "SigridBuene", "city": "Narvik", "userpic_url": "https://drscdn.500px.org/user_avatar/257270/q%3D85_w%3D300_h%3D300/v2?webp=true&v=15&sig=b1b537451badd405006a635d054f94ffe2a99b8c981cc07d2a6a16ba96a996a3", "store_on": true, "userpic_https_url": "https://drscdn.500px.org/user_avatar/257270/q%3D85_w%3D300_h%3D300/v2?webp=true&v=15&sig=b1b537451badd405006a635d054f94ffe2a99b8c981cc07d2a6a16ba96a996a3", "firstname": "Sigrid", "lastname": "Buene", "upgrade_status": 3, "avatars": {"default": {"https": "https://drscdn.500px.org/user_avatar/257270/q%3D85_w%3D300_h%3D300/v2?webp=true&v=15&sig=b1b537451badd405006a635d054f94ffe2a99b8c981cc07d2a6a16ba96a996a3"}, "large": {"https": "https://drscdn.500px.org/user_avatar/257270/q%3D85_w%3D100_h%3D100/v2?webp=true&v=15&sig=25014fef1cd6ff0003dbd44ced9f503aa5ae4d173f6531cfd65ecb1f08bae19c"}, "small": {"https": "https://drscdn.500px.org/user_avatar/257270/q%3D85_w%3D50_h%3D50/v2?webp=true&v=15&sig=b72a676b1a07b0245ead8cc8e9e9b1e2e9e7be8cd89d9180e39c3dee803aef3d"}, "tiny": {"https": "https://drscdn.500px.org/user_avatar/257270/q%3D85_w%3D30_h%3D30/v2?webp=true&v=15&sig=a5e227d323df91a8ec7e830b029e2b903873be42fdf79fd82a8404cc484399c0"}}, "cover_url": "https://drscdn.500px.org/user_cover/257270/q%3D65_m%3D2048/v2?webp=true&v=24&sig=c6b849bbbaa64db6e2dae1fe5b457d92a1e65df2e9641e7ce6c32bcbb17d29bc", "usertype": 10, "followers_count": 112321, "country": "Norway", "fullname": "Sigrid Buene", "id": 257270, "affection": 147757}, {"username": "rajweb", "city": "Nashville", "userpic_url": "https://drscdn.500px.org/user_avatar/79780/q%3D85_w%3D300_h%3D300/v2?webp=true&v=4&sig=c2f8a501292da38cfd93e72c8fedf660b9ad5d2515a4ad19dda8eb8cd0d42383", "store_on": true, "userpic_https_url": "https://drscdn.500px.org/user_avatar/79780/q%3D85_w%3D300_h%3D300/v2?webp=true&v=4&sig=c2f8a501292da38cfd93e72c8fedf660b9ad5d2515a4ad19dda8eb8cd0d42383", "firstname": "Raj", "lastname": "Gupta", "upgrade_status": 0, "avatars": {"default": {"https": "https://drscdn.500px.org/user_avatar/79780/q%3D85_w%3D300_h%3D300/v2?webp=true&v=4&sig=c2f8a501292da38cfd93e72c8fedf660b9ad5d2515a4ad19dda8eb8cd0d42383"}, "large": {"https": "https://drscdn.500px.org/user_avatar/79780/q%3D85_w%3D100_h%3D100/v2?webp=true&v=4&sig=4835a91afa146471df5e0c7cda5e961157e41eee9ac17d13ea7583ab4d3edc6a"}, "small": {"https": "https://drscdn.500px.org/user_avatar/79780/q%3D85_w%3D50_h%3D50/v2?webp=true&v=4&sig=da99ba36201413e6d2bbb4abeac75b8d8b8035475886b74fa70fa3487454605c"}, "tiny": {"https": "https://drscdn.500px.org/user_avatar/79780/q%3D85_w%3D30_h%3D30/v2?webp=true&v=4&sig=a5dbb0bc79e537a2675d02aea42f5638dca6ee46c0079887a0d804a87407b286"}}, "cover_url": "https://drscdn.500px.org/user_cover/79780/q%3D65_m%3D2048/v2?webp=true&v=8&sig=e1b5a17db3cd471da249d9987b3efe06e0d8fefd45c440dc5cd8bad76696f853", "usertype": 0, "followers_count": 143, "country": "United States", "fullname": "Raj Gupta", "id": 79780, "affection": 6151}], "page": 1, "friends_count": 22, "friends_pages": 2}{"friends": [{"username": "shalenkin", "city": "Novosibirsk", "userpic_url": "https://drscdn.500px.org/user_avatar/23281/q%3D85_w%3D300_h%3D300/v2?webp=true&v=86&sig=f0ea90898d8f230ea170c455b8c82bfe0b9a9cd788a298ebf915220215d1cdea", "store_on": true, "userpic_https_url": "https://drscdn.500px.org/user_avatar/23281/q%3D85_w%3D300_h%3D300/v2?webp=true&v=86&sig=f0ea90898d8f230ea170c455b8c82bfe0b9a9cd788a298ebf915220215d1cdea", "firstname": "Roman", "lastname": "Shalenkin", "upgrade_status": 0, "avatars": {"default": {"https": "https://drscdn.500px.org/user_avatar/23281/q%3D85_w%3D300_h%3D300/v2?webp=true&v=86&sig=f0ea90898d8f230ea170c455b8c82bfe0b9a9cd788a298ebf915220215d1cdea"}, "large": {"https": "https://drscdn.500px.org/user_avatar/23281/q%3D85_w%3D100_h%3D100/v2?webp=true&v=86&sig=9ce968e164d458671c66a88ce1cf94538cc975490a557f12f921ed955bd2b0a9"}, "small": {"https": "https://drscdn.500px.org/user_avatar/23281/q%3D85_w%3D50_h%3D50/v2?webp=true&v=86&sig=ae5ec885f69ffba02b800a1f15afcb0c1fb5476c173ac6fbb8b8490a7b54f72c"}, "tiny": {"https": "https://drscdn.500px.org/user_avatar/23281/q%3D85_w%3D30_h%3D30/v2?webp=true&v=86&sig=c2961223b620c636edbdc432b80936a33a0059c14ca5eb8fdd0bdfe0283018f3"}}, "cover_url": "https://drscdn.500px.org/user_cover/23281/q%3D65_m%3D2048/v2?webp=true&v=8&sig=58b11af86525b18796d60286c3adab7a2619bb561225206850308b697aaa1f99", "usertype": 0, "followers_count": 12789, "country": "Russia", "fullname": "Roman Shalenkin", "id": 23281, "affection": 40952}, {"username": "natta", "city": "Toronto", "userpic_url": "https://drscdn.500px.org/user_avatar/1607/q%3D85_w%3D300_h%3D300/v2?webp=true&v=2&sig=0a557fa55fb790e3b30de34e7f971f137dfe810f9744acd5ea30ba3643aa674f", "store_on": true, "userpic_https_url": "https://drscdn.500px.org/user_avatar/1607/q%3D85_w%3D300_h%3D300/v2?webp=true&v=2&sig=0a557fa55fb790e3b30de34e7f971f137dfe810f9744acd5ea30ba3643aa674f", "firstname": "Natta", "lastname": "Summerky", "upgrade_status": 0, "avatars": {"default": {"https": "https://drscdn.500px.org/user_avatar/1607/q%3D85_w%3D300_h%3D300/v2?webp=true&v=2&sig=0a557fa55fb790e3b30de34e7f971f137dfe810f9744acd5ea30ba3643aa674f"}, "large": {"https": "https://drscdn.500px.org/user_avatar/1607/q%3D85_w%3D100_h%3D100/v2?webp=true&v=2&sig=4941d61b55a9e4d83125a642005dc50f1002e05f073d71c0bd7ee5c5f0f0bb3b"}, "small": {"https": "https://drscdn.500px.org/user_avatar/1607/q%3D85_w%3D50_h%3D50/v2?webp=true&v=2&sig=4aeacb3b1ff96dc0305132d2b5852b7e0fd6e0d8477d6c0c13d6d8984d8c6408"}, "tiny": {"https": "https://drscdn.500px.org/user_avatar/1607/q%3D85_w%3D30_h%3D30/v2?webp=true&v=2&sig=b84790b10d14407641e35ddcf90f434fb3cd3b06752129167a575a8d68af7ec1"}}, "cover_url": "https://drscdn.500px.org/user_cover/1607/q%3D65_m%3D2048/v2?webp=true&v=11&sig=984a4f8b0df935a811320189273e100feeb7c64a1499e1ad616f25d6adc451ca", "usertype": 13, "followers_count": 8271, "country": "Canada", "fullname": "Natta Summerky", "id": 1607, "affection": 50804}], "page": 2, "friends_count": 22, "friends_pages": 2}